setup.py
sainandanadipkg/__init__.py
sainandanadipkg/calculator.py
sainandanadipkg.egg-info/PKG-INFO
sainandanadipkg.egg-info/SOURCES.txt
sainandanadipkg.egg-info/dependency_links.txt
sainandanadipkg.egg-info/top_level.txt