Metadata-Version: 2.1
Name: sainandanadipkg
Version: 0.0.1
Summary: ADI Python Package Calculator module
Home-page: https://github.com/SainandanD/mydemopackage
Author: sainandan
Author-email: nandansaid@gmail.com
Classifier: Programming Language :: Python :: 3
Classifier: Operating System :: OS Independent
